vision_architectures/__init__.py
vision_architectures/_modidx.py
vision_architectures/docstrings.py
vision_architectures/blocks/__init__.py
vision_architectures/blocks/cnn.py
vision_architectures/blocks/heads_3d.py
vision_architectures/blocks/mbconv_3d.py
vision_architectures/blocks/se.py
vision_architectures/blocks/transformer.py
vision_architectures/image_readers/__init__.py
vision_architectures/image_readers/safetensors_reader.py
vision_architectures/layers/__init__.py
vision_architectures/layers/attention.py
vision_architectures/layers/codebook.py
vision_architectures/layers/embeddings.py
vision_architectures/layers/latent_space.py
vision_architectures/layers/scale.py
vision_architectures/losses/__init__.py
vision_architectures/losses/class_balanced_cross_entropy_loss.py
vision_architectures/metrics/__init__.py
vision_architectures/metrics/detection.py
vision_architectures/nets/__init__.py
vision_architectures/nets/cait_3d.py
vision_architectures/nets/detr_3d.py
vision_architectures/nets/fpn_2d.py
vision_architectures/nets/fpn_3d.py
vision_architectures/nets/maxvit_3d.py
vision_architectures/nets/perceiver_3d.py
vision_architectures/nets/swin_3d.py
vision_architectures/nets/swinv2_3d.py
vision_architectures/nets/symswin_3d.py
vision_architectures/nets/unetr_3d_decoder.py
vision_architectures/nets/upernet_2d.py
vision_architectures/nets/upernet_3d.py
vision_architectures/nets/vit_3d.py
vision_architectures/schedulers/__init__.py
vision_architectures/schedulers/cyclic.py
vision_architectures/schedulers/lrs.py
vision_architectures/schedulers/noise.py
vision_architectures/schedulers/sigmoid.py
vision_architectures/transforms/__init__.py
vision_architectures/transforms/clipping.py
vision_architectures/transforms/croppad.py
vision_architectures/transforms/resize.py
vision_architectures/transforms/spatial.py
vision_architectures/utils/__init__.py
vision_architectures/utils/activation_checkpointing.py
vision_architectures/utils/activations.py
vision_architectures-1.0.dist-info/licenses/LICENSE
vision_architectures-1.0.dist-info/METADATA
vision_architectures-1.0.dist-info/WHEEL
vision_architectures-1.0.dist-info/entry_points.txt
vision_architectures-1.0.dist-info/top_level.txt
vision_architectures-1.0.dist-info/RECORD
