Metadata-Version: 2.4
Name: vision_architectures
Version: 1.0
Summary: Vision architectures
Home-page: https://github.com/arjunagarwal899/vision_architectures
Author: Arjun Agarwal
Author-email: arjunagarwal899@gmail.com
License: GNU General Public License v3
Keywords: nbdev jupyter notebook python
Classifier: Development Status :: 5 - Production/Stable
Classifier: Intended Audience :: Developers
Classifier: Natural Language :: English
Classifier: Programming Language :: Python :: 3.10
Classifier: Programming Language :: Python :: 3.11
Classifier: License :: OSI Approved :: GNU General Public License v3 (GPLv3)
Requires-Python: >=3.10
License-File: LICENSE
Requires-Dist: einops
Requires-Dist: huggingface_hub
Requires-Dist: loguru
Requires-Dist: monai
Requires-Dist: munch
Requires-Dist: nbdev
Requires-Dist: numpy
Requires-Dist: pre-commit
Requires-Dist: pydantic
Requires-Dist: safetensors
Requires-Dist: scipy
Requires-Dist: torch
Requires-Dist: torchmetrics
Provides-Extra: dev
Requires-Dist: matplotlib; extra == "dev"
Dynamic: author
Dynamic: author-email
Dynamic: classifier
Dynamic: description
Dynamic: description-content-type
Dynamic: home-page
Dynamic: keywords
Dynamic: license
Dynamic: license-file
Dynamic: provides-extra
Dynamic: requires-dist
Dynamic: requires-python
Dynamic: summary
